pwm.vhd
library IEEE;
use IEEE.STD_LOGIC_1164.ALL;
use IEEE.STD_LOGIC_ARITH.ALL;
use IEEE.STD_LOGIC_UNSIGNED.ALL;

entity pwm_control is
    generic(
        MAX_CPT : integer := 20000 --represente le nombre de tics dans un cycle 1MHz/50 Hz = 20000
    );
    Port (
        clk : in std_logic;

        duty : in integer range 0 to MAX_CPT; -- Avec duty = 0 tOFF 100% et = MAX_CPT tOn = 100%
        en : in std_logic;
        rst : in std_logic;
        pwm : out std_logic;
        NegPwm : out std_logic 
    );
end pwm_control;

architecture pwm_control_arch of pwm_control is
    signal counter : integer range 0 to MAX_CPT := 0;
begin
    process (clk, rst)
    begin

        if rst = '0' then
            counter <= 0;
            pwm <= '0';
            NegPwm <= '1';
        elsif rising_edge(clk) and en = '0' then
            -- traitement du signal pwn
            if counter < duty then
                pwm <= '1';
                NegPwm <= '0';
            else
                pwm <= '0';
                NegPwm <= '1';
            end if;

            if counter < MAX_CPT -1 then
                counter <= counter + 1;
            else
                counter <= 0;
            end if;
                
        end if;
    end process;
end pwm_control_arch;

hall_sensor.vhd
-- Definition des librairies
library IEEE;
library WORK;

-- Definition des portee d'utilisation
use IEEE.std_logic_1164.all;
use IEEE.std_logic_arith.all;
use IEEE.std_logic_unsigned.all;

-- -----------------------------------------------------------------------------
-- Definition de l'entite
-- -----------------------------------------------------------------------------
entity hall_sensor is

	-- definition des parametres generiques
	generic	(
		-- largeur du bus de donnees par defaut
		MAX_CPT : integer := 20000
	);

	-- definition des entrees/sorties
	port 	(
		clk      		: in std_logic; 
        EN				: in std_logic; 
        RST				: in std_logic; 

		sig1 	        : out std_logic;
        sig2 	        : out std_logic; 
        sig3 	        : out std_logic
    );
end hall_sensor ;


architecture hall_sensor_arch of hall_sensor is
    constant PHASE_SHIFT : natural := MAX_CPT /3;

    type state_type is (S1, S2, S3);
    signal current_state : state_type;
    signal count : natural range 0 to PHASE_SHIFT := 0;
begin

    P_state : process (RST, clk)
    begin
        if count = PHASE_SHIFT then
            count <= 0;
        end if;

        if RST = '0' then 
            current_state <= S1;
        elsif rising_edge(clk) and EN = '0'  then

            if count = PHASE_SHIFT-1 then 
                if current_state = S1 then
                    current_state <= S2;
                elsif current_state = S2 then
                    current_state <= S3;
                else 
                    current_state <= S1;
                end if;

            end if;

            count <= count +1;
        end if;
    end process P_state;

    sig1 <= '1' when current_state = S1 else '0';
    sig2 <= '1' when current_state = S2 else '0';
    sig3 <= '1' when current_state = S3 else '0';

end hall_sensor_arch;

BLDC_controller.vhd
-- Definition des librairies
library IEEE;
library WORK;

-- Definition des portee d'utilisation
use IEEE.std_logic_1164.all;
use IEEE.std_logic_arith.all;
use IEEE.std_logic_unsigned.all;

-- -----------------------------------------------------------------------------
-- Definition de l'entite
-- -----------------------------------------------------------------------------
entity BLDC_controller is

	-- definition des parametres generiques
	generic	(
		-- largeur du bus de donnees par defaut
		MAX_CPT : integer := 20000
	);

	-- definition des entrees/sorties
	port 	(
		--  Ports d'entré du controlleur'
		clk      		: in std_logic; 
        EN				: in std_logic; 
        RST				: in std_logic; 
		DUTY	    	: in integer range 0 to MAX_CPT; -- Avec duty = 0 tOFF 100% et = MAX_CPT tOn = 100%

		-- Ports de sortie du controlleur 
        U				: out std_logic; 
        V				: out std_logic; 
        W				: out std_logic; 
        
        Wn				: out std_logic; 
        Vn				: out std_logic; 
        Un				: out std_logic
    );
end BLDC_controller;


architecture BLDC_controller_arch of BLDC_controller is
    constant PHASE_SHIFT : integer := MAX_CPT / 3; -- 120 degrés de décalage
    signal rst_1 : std_logic := '0';
    signal rst_2 : std_logic := '0';
    signal rst_3 : std_logic := '0';

    signal sig1 : std_logic;
    signal sig2 : std_logic; 
    signal sig3 : std_logic;

    signal duty_1 : integer range 0 to MAX_CPT;
    signal duty_2 : integer range 0 to MAX_CPT;
    signal duty_3 : integer range 0 to MAX_CPT;
begin

    P_HALL_sensor :  entity work.hall_sensor(hall_sensor_arch)
    generic map(MAX_CPT)
    port map(
       clk => clk,
       en => en,
       rst => rst,
       sig1 => sig1,
       sig2 => sig2,
       sig3 => sig3
    );

    rst_1 <= RST when (sig1'event and sig1 = '1');
    rst_2 <= RST when (sig2'event and sig2 = '1');
    rst_3 <= RST when (sig3'event and sig3 = '1');

    duty_1 <= DUTY when (sig1'event and sig1 = '1');
    duty_2 <= DUTY when (sig2'event and sig2 = '1');
    duty_3 <= DUTY when (sig3'event and sig3 = '1');
    

    PWM_1 : entity work.pwm_control(pwm_control_arch)
         generic map(MAX_CPT)
         port map(
            clk => clk,
            duty => duty_1,
            en => en,
            rst => rst_1,
            pwm => U,
            NegPwm => Un
         );

    PWM_2 : entity work.pwm_control(pwm_control_arch)
         generic map(MAX_CPT)
         port map(
            clk => clk,
            duty => duty_2,
            en => en,
            rst => rst_2,
            pwm => V,
            NegPwm => Vn
         );

    PWM_3 : entity work.pwm_control(pwm_control_arch)
         generic map(MAX_CPT)
         port map(
            clk => clk,
            duty => duty_3,
            en => en,
            rst => rst_3,
            pwm => W,
            NegPwm => Wn
         );

end BLDC_controller_arch;

test_BLDC_controller.vhd
-- Definition des librairies
library IEEE;
library WORK;

-- Definition des portee d'utilisation
use IEEE.std_logic_1164.all;
use IEEE.std_logic_arith.all;
use IEEE.std_logic_unsigned.all;

-- -----------------------------------------------------------------------------
-- Definition de l'entite
-- -----------------------------------------------------------------------------
entity test_BLDC_controller is
end test_BLDC_controller;


architecture test_BLDC_controller_arch of test_BLDC_controller is
	
	-- definition des constantes
	constant clk_pulse : time := 5 ns;
	constant E_MAX_CPT : natural := 6;
	constant TIMEOUT : time := 1000 ns;

	-- definition des signaux
	signal E_clk : std_logic; 
	signal E_EN : std_logic; 
	signal E_RST : std_logic; 
	signal E_DUTY : integer range 0 to E_MAX_CPT := 0; 

	signal E_U : std_logic; 
	signal E_V : std_logic; 
	signal E_W : std_logic; 
	signal E_Un : std_logic; 
	signal E_Vn : std_logic; 
	signal E_Wn : std_logic; 

begin

	-- création de l'horloge et TIMEOUT
	P_CLK : process
	begin
		E_clk <= '1';
		wait for clk_pulse;
		E_clk <= '0';
		wait for clk_pulse;
	end process P_CLK;
	
	P_TIMEOUT : process
	begin
		wait for TIMEOUT;
		assert FALSE report "TIMEOUT SIMULATION !!!" severity FAILURE;
	end process P_TIMEOUT;
	
	-- instanciation et mapping du composant BLDC_controller
	BLDC_controller : entity work.BLDC_controller(BLDC_controller_arch)
			generic map (E_MAX_CPT)
			port map (E_clk, E_EN, E_RST, E_DUTY, E_U, E_V, E_W, E_Un, E_Vn, E_Wn);

	-- realisation des test
	
	P_TEST : process 
	begin 

		E_EN <= '0';
		E_RST <= '0';

		wait for clk_pulse * 3 ;
		E_RST <= '1';

		wait until E_clk = '1';

		for i in 0 to E_MAX_CPT-1 loop
			wait for clk_pulse * 2 * E_MAX_CPT ;
			E_DUTY <= E_DUTY + 1;
			end loop;
		
		wait for clk_pulse * 4 * E_MAX_CPT ;
		wait until E_clk = '1';

		for i in E_MAX_CPT-1 downto 0 loop
			wait for clk_pulse * 2 * E_MAX_CPT ;
			E_DUTY <= E_DUTY - 1;
			end loop;

		wait for clk_pulse * 6 ;
		assert FALSE report "FIN DE SIMULATION" severity FAILURE;

	
	end process P_TEST;
end test_BLDC_controller_arch;

test_BLDC_controller.vcd
$date
  Thu Apr  3 13:31:49 2025
$end
$version
  GHDL v0
$end
$timescale
  1 fs
$end
$scope module standard $end
$upscope $end
$scope module std_logic_1164 $end
$upscope $end
$scope module std_logic_arith $end
$upscope $end
$scope module std_logic_unsigned $end
$upscope $end
$scope module test_bldc_controller $end
$var reg 1 ! e_clk $end
$var reg 1 " e_en $end
$var reg 1 # e_rst $end
$var integer 32 $ e_duty $end
$var reg 1 % e_u $end
$var reg 1 & e_v $end
$var reg 1 ' e_w $end
$var reg 1 ( e_un $end
$var reg 1 ) e_vn $end
$var reg 1 * e_wn $end
$scope module bldc_controller $end
$var reg 1 + clk $end
$var reg 1 , en $end
$var reg 1 - rst $end
$var integer 32 . duty $end
$var reg 1 / u $end
$var reg 1 0 v $end
$var reg 1 1 w $end
$var reg 1 2 wn $end
$var reg 1 3 vn $end
$var reg 1 4 un $end
$var reg 1 5 rst_1 $end
$var reg 1 6 rst_2 $end
$var reg 1 7 rst_3 $end
$var reg 1 8 sig1 $end
$var reg 1 9 sig2 $end
$var reg 1 : sig3 $end
$var integer 32 ; duty_1 $end
$var integer 32 < duty_2 $end
$var integer 32 = duty_3 $end
$scope module p_hall_sensor $end
$var reg 1 > clk $end
$var reg 1 ? en $end
$var reg 1 @ rst $end
$var reg 1 A sig1 $end
$var reg 1 B sig2 $end
$var reg 1 C sig3 $end
$comment current_state is not handled $end
$var integer 32 D count $end
$upscope $end
$scope module pwm_1 $end
$var reg 1 E clk $end
$var integer 32 F duty $end
$var reg 1 G en $end
$var reg 1 H rst $end
$var reg 1 I pwm $end
$var reg 1 J negpwm $end
$var integer 32 K counter $end
$upscope $end
$scope module pwm_2 $end
$var reg 1 L clk $end
$var integer 32 M duty $end
$var reg 1 N en $end
$var reg 1 O rst $end
$var reg 1 P pwm $end
$var reg 1 Q negpwm $end
$var integer 32 R counter $end
$upscope $end
$scope module pwm_3 $end
$var reg 1 S clk $end
$var integer 32 T duty $end
$var reg 1 U en $end
$var reg 1 V rst $end
$var reg 1 W pwm $end
$var reg 1 X negpwm $end
$var integer 32 Y counter $end
$upscope $end
$upscope $end
$upscope $end
$enddefinitions $end
#0
1!
0"
0#
b0 $
0%
0&
0'
1(
1)
1*
1+
0,
0-
b0 .
0/
00
01
12
13
14
05
06
07
18
09
0:
b0 ;
b0 <
b0 =
1>
0?
0@
1A
0B
0C
b0 D
1E
b0 F
0G
0H
0I
1J
b0 K
1L
b0 M
0N
0O
0P
1Q
b0 R
1S
b0 T
0U
0V
0W
1X
b0 Y
#5000000
0!
0+
0>
0E
0L
0S
#10000000
1!
1+
1>
1E
1L
1S
#15000000
0!
1#
0+
1-
0>
1@
0E
0L
0S
#20000000
1!
1+
1>
b1 D
1E
1L
1S
#25000000
0!
0+
0>
0E
0L
0S
#30000000
1!
1+
16
08
19
1>
0A
1B
b10 D
1E
1L
1O
1S
#35000000
0!
0+
0>
b0 D
0E
0L
0S
#40000000
1!
1+
1>
b1 D
1E
1L
b1 R
1S
#45000000
0!
0+
0>
0E
0L
0S
#50000000
1!
1+
17
09
1:
1>
0B
1C
b10 D
1E
1L
b10 R
1S
1V
#55000000
0!
0+
0>
b0 D
0E
0L
0S
#60000000
1!
1+
1>
b1 D
1E
1L
b11 R
1S
b1 Y
#65000000
0!
0+
0>
0E
0L
0S
#70000000
1!
1+
15
18
0:
1>
1A
0C
b10 D
1E
1H
1L
b100 R
1S
b10 Y
#75000000
0!
0+
0>
b0 D
0E
0L
0S
#80000000
1!
b1 $
1+
b1 .
1>
b1 D
1E
b1 K
1L
b101 R
1S
b11 Y
#85000000
0!
0+
0>
0E
0L
0S
#90000000
1!
1+
08
19
b1 <
1>
0A
1B
b10 D
1E
b10 K
1L
b1 M
b0 R
1S
b100 Y
#95000000
0!
0+
0>
b0 D
0E
0L
0S
#100000000
1!
1&
0)
1+
10
03
1>
b1 D
1E
b11 K
1L
1P
0Q
b1 R
1S
b101 Y
#105000000
0!
0+
0>
0E
0L
0S
#110000000
1!
0&
1)
1+
00
13
09
1:
b1 =
1>
0B
1C
b10 D
1E
b100 K
1L
0P
1Q
b10 R
1S
b1 T
b0 Y
#115000000
0!
0+
0>
b0 D
0E
0L
0S
#120000000
1!
1'
0(
1+
11
02
1>
b1 D
1E
b101 K
1L
b11 R
1S
1W
0X
b1 Y
#125000000
0!
0+
0>
0E
0L
0S
#130000000
1!
0'
1(
1+
01
12
18
0:
b1 ;
1>
1A
0C
b10 D
1E
b1 F
b0 K
1L
b100 R
1S
0W
1X
b10 Y
#135000000
0!
0+
0>
b0 D
0E
0L
0S
#140000000
1!
b10 $
1%
0*
1+
b10 .
1/
04
1>
b1 D
1E
1I
0J
b1 K
1L
b101 R
1S
b11 Y
#145000000
0!
0+
0>
0E
0L
0S
#150000000
1!
0%
1*
1+
0/
14
08
19
b10 <
1>
0A
1B
b10 D
1E
0I
1J
b10 K
1L
b10 M
b0 R
1S
b100 Y
#155000000
0!
0+
0>
b0 D
0E
0L
0S
#160000000
1!
1&
0)
1+
10
03
1>
b1 D
1E
b11 K
1L
1P
0Q
b1 R
1S
b101 Y
#165000000
0!
0+
0>
0E
0L
0S
#170000000
1!
1+
09
1:
b10 =
1>
0B
1C
b10 D
1E
b100 K
1L
b10 R
1S
b10 T
b0 Y
#175000000
0!
0+
0>
b0 D
0E
0L
0S
#180000000
1!
0&
1'
0(
1)
1+
00
11
02
13
1>
b1 D
1E
b101 K
1L
0P
1Q
b11 R
1S
1W
0X
b1 Y
#185000000
0!
0+
0>
0E
0L
0S
#190000000
1!
1+
18
0:
b10 ;
1>
1A
0C
b10 D
1E
b10 F
b0 K
1L
b100 R
1S
b10 Y
#195000000
0!
0+
0>
b0 D
0E
0L
0S
#200000000
1!
b11 $
1%
0'
1(
0*
1+
b11 .
1/
01
12
04
1>
b1 D
1E
1I
0J
b1 K
1L
b101 R
1S
0W
1X
b11 Y
#205000000
0!
0+
0>
0E
0L
0S
#210000000
1!
1+
08
19
b11 <
1>
0A
1B
b10 D
1E
b10 K
1L
b11 M
b0 R
1S
b100 Y
#215000000
0!
0+
0>
b0 D
0E
0L
0S
#220000000
1!
0%
1&
0)
1*
1+
0/
10
03
14
1>
b1 D
1E
0I
1J
b11 K
1L
1P
0Q
b1 R
1S
b101 Y
#225000000
0!
0+
0>
0E
0L
0S
#230000000
1!
1+
09
1:
b11 =
1>
0B
1C
b10 D
1E
b100 K
1L
b10 R
1S
b11 T
b0 Y
#235000000
0!
0+
0>
b0 D
0E
0L
0S
#240000000
1!
1'
0(
1+
11
02
1>
b1 D
1E
b101 K
1L
b11 R
1S
1W
0X
b1 Y
#245000000
0!
0+
0>
0E
0L
0S
#250000000
1!
0&
1)
1+
00
13
18
0:
b11 ;
1>
1A
0C
b10 D
1E
b11 F
b0 K
1L
0P
1Q
b100 R
1S
b10 Y
#255000000
0!
0+
0>
b0 D
0E
0L
0S
#260000000
1!
b100 $
1%
0*
1+
b100 .
1/
04
1>
b1 D
1E
1I
0J
b1 K
1L
b101 R
1S
b11 Y
#265000000
0!
0+
0>
0E
0L
0S
#270000000
1!
0'
1(
1+
01
12
08
19
b100 <
1>
0A
1B
b10 D
1E
b10 K
1L
b100 M
b0 R
1S
0W
1X
b100 Y
#275000000
0!
0+
0>
b0 D
0E
0L
0S
#280000000
1!
1&
0)
1+
10
03
1>
b1 D
1E
b11 K
1L
1P
0Q
b1 R
1S
b101 Y
#285000000
0!
0+
0>
0E
0L
0S
#290000000
1!
0%
1*
1+
0/
14
09
1:
b100 =
1>
0B
1C
b10 D
1E
0I
1J
b100 K
1L
b10 R
1S
b100 T
b0 Y
#295000000
0!
0+
0>
b0 D
0E
0L
0S
#300000000
1!
1'
0(
1+
11
02
1>
b1 D
1E
b101 K
1L
b11 R
1S
1W
0X
b1 Y
#305000000
0!
0+
0>
0E
0L
0S
#310000000
1!
1+
18
0:
b100 ;
1>
1A
0C
b10 D
1E
b100 F
b0 K
1L
b100 R
1S
b10 Y
#315000000
0!
0+
0>
b0 D
0E
0L
0S
#320000000
1!
b101 $
1%
0&
1)
0*
1+
b101 .
1/
00
13
04
1>
b1 D
1E
1I
0J
b1 K
1L
0P
1Q
b101 R
1S
b11 Y
#325000000
0!
0+
0>
0E
0L
0S
#330000000
1!
1+
08
19
b101 <
1>
0A
1B
b10 D
1E
b10 K
1L
b101 M
b0 R
1S
b100 Y
#335000000
0!
0+
0>
b0 D
0E
0L
0S
#340000000
1!
1&
0'
1(
0)
1+
10
01
12
03
1>
b1 D
1E
b11 K
1L
1P
0Q
b1 R
1S
0W
1X
b101 Y
#345000000
0!
0+
0>
0E
0L
0S
#350000000
1!
1+
09
1:
b101 =
1>
0B
1C
b10 D
1E
b100 K
1L
b10 R
1S
b101 T
b0 Y
#355000000
0!
0+
0>
b0 D
0E
0L
0S
#360000000
1!
0%
1'
0(
1*
1+
0/
11
02
14
1>
b1 D
1E
0I
1J
b101 K
1L
b11 R
1S
1W
0X
b1 Y
#365000000
0!
0+
0>
0E
0L
0S
#370000000
1!
1+
18
0:
b101 ;
1>
1A
0C
b10 D
1E
b101 F
b0 K
1L
b100 R
1S
b10 Y
#375000000
0!
0+
0>
b0 D
0E
0L
0S
#380000000
1!
b110 $
1%
0*
1+
b110 .
1/
04
1>
b1 D
1E
1I
0J
b1 K
1L
b101 R
1S
b11 Y
#385000000
0!
0+
0>
0E
0L
0S
#390000000
1!
0&
1)
1+
00
13
08
19
b110 <
1>
0A
1B
b10 D
1E
b10 K
1L
b110 M
0P
1Q
b0 R
1S
b100 Y
#395000000
0!
0+
0>
b0 D
0E
0L
0S
#400000000
1!
1&
0)
1+
10
03
1>
b1 D
1E
b11 K
1L
1P
0Q
b1 R
1S
b101 Y
#405000000
0!
0+
0>
0E
0L
0S
#410000000
1!
0'
1(
1+
01
12
09
1:
b110 =
1>
0B
1C
b10 D
1E
b100 K
1L
b10 R
1S
b110 T
0W
1X
b0 Y
#415000000
0!
0+
0>
b0 D
0E
0L
0S
#420000000
1!
1'
0(
1+
11
02
1>
b1 D
1E
b101 K
1L
b11 R
1S
1W
0X
b1 Y
#425000000
0!
0+
0>
0E
0L
0S
#430000000
1!
0%
1*
1+
0/
14
18
0:
b110 ;
1>
1A
0C
b10 D
1E
b110 F
0I
1J
b0 K
1L
b100 R
1S
b10 Y
#435000000
0!
0+
0>
b0 D
0E
0L
0S
#440000000
1!
1%
0*
1+
1/
04
1>
b1 D
1E
1I
0J
b1 K
1L
b101 R
1S
b11 Y
#445000000
0!
0+
0>
0E
0L
0S
#450000000
1!
1+
08
19
1>
0A
1B
b10 D
1E
b10 K
1L
b0 R
1S
b100 Y
#455000000
0!
0+
0>
b0 D
0E
0L
0S
#460000000
1!
1+
1>
b1 D
1E
b11 K
1L
b1 R
1S
b101 Y
#465000000
0!
0+
0>
0E
0L
0S
#470000000
1!
1+
09
1:
1>
0B
1C
b10 D
1E
b100 K
1L
b10 R
1S
b0 Y
#475000000
0!
0+
0>
b0 D
0E
0L
0S
#480000000
1!
1+
1>
b1 D
1E
b101 K
1L
b11 R
1S
b1 Y
#485000000
0!
0+
0>
0E
0L
0S
#490000000
1!
1+
18
0:
1>
1A
0C
b10 D
1E
b0 K
1L
b100 R
1S
b10 Y
#495000000
0!
0+
0>
b0 D
0E
0L
0S
#500000000
1!
1+
1>
b1 D
1E
b1 K
1L
b101 R
1S
b11 Y
#505000000
0!
0+
0>
0E
0L
0S
#510000000
1!
1+
08
19
1>
0A
1B
b10 D
1E
b10 K
1L
b0 R
1S
b100 Y
#515000000
0!
0+
0>
b0 D
0E
0L
0S
#520000000
1!
1+
1>
b1 D
1E
b11 K
1L
b1 R
1S
b101 Y
#525000000
0!
0+
0>
0E
0L
0S
#530000000
1!
1+
09
1:
1>
0B
1C
b10 D
1E
b100 K
1L
b10 R
1S
b0 Y
#535000000
0!
0+
0>
b0 D
0E
0L
0S
#540000000
1!
1+
1>
b1 D
1E
b101 K
1L
b11 R
1S
b1 Y
#545000000
0!
0+
0>
0E
0L
0S
#550000000
1!
1+
18
0:
1>
1A
0C
b10 D
1E
b0 K
1L
b100 R
1S
b10 Y
#555000000
0!
0+
0>
b0 D
0E
0L
0S
#560000000
1!
b101 $
1+
b101 .
1>
b1 D
1E
b1 K
1L
b101 R
1S
b11 Y
#565000000
0!
0+
0>
0E
0L
0S
#570000000
1!
1+
08
19
b101 <
1>
0A
1B
b10 D
1E
b10 K
1L
b101 M
b0 R
1S
b100 Y
#575000000
0!
0+
0>
b0 D
0E
0L
0S
#580000000
1!
1+
1>
b1 D
1E
b11 K
1L
b1 R
1S
b101 Y
#585000000
0!
0+
0>
0E
0L
0S
#590000000
1!
1+
09
1:
b101 =
1>
0B
1C
b10 D
1E
b100 K
1L
b10 R
1S
b101 T
b0 Y
#595000000
0!
0+
0>
b0 D
0E
0L
0S
#600000000
1!
1+
1>
b1 D
1E
b101 K
1L
b11 R
1S
b1 Y
#605000000
0!
0+
0>
0E
0L
0S
#610000000
1!
1+
18
0:
b101 ;
1>
1A
0C
b10 D
1E
b101 F
b0 K
1L
b100 R
1S
b10 Y
#615000000
0!
0+
0>
b0 D
0E
0L
0S
#620000000
1!
b100 $
1+
b100 .
1>
b1 D
1E
b1 K
1L
b101 R
1S
b11 Y
#625000000
0!
0+
0>
0E
0L
0S
#630000000
1!
0&
1)
1+
00
13
08
19
b100 <
1>
0A
1B
b10 D
1E
b10 K
1L
b100 M
0P
1Q
b0 R
1S
b100 Y
#635000000
0!
0+
0>
b0 D
0E
0L
0S
#640000000
1!
1&
0)
1+
10
03
1>
b1 D
1E
b11 K
1L
1P
0Q
b1 R
1S
b101 Y
#645000000
0!
0+
0>
0E
0L
0S
#650000000
1!
0'
1(
1+
01
12
09
1:
b100 =
1>
0B
1C
b10 D
1E
b100 K
1L
b10 R
1S
b100 T
0W
1X
b0 Y
#655000000
0!
0+
0>
b0 D
0E
0L
0S
#660000000
1!
1'
0(
1+
11
02
1>
b1 D
1E
b101 K
1L
b11 R
1S
1W
0X
b1 Y
#665000000
0!
0+
0>
0E
0L
0S
#670000000
1!
0%
1*
1+
0/
14
18
0:
b100 ;
1>
1A
0C
b10 D
1E
b100 F
0I
1J
b0 K
1L
b100 R
1S
b10 Y
#675000000
0!
0+
0>
b0 D
0E
0L
0S
#680000000
1!
b11 $
1%
0&
1)
0*
1+
b11 .
1/
00
13
04
1>
b1 D
1E
1I
0J
b1 K
1L
0P
1Q
b101 R
1S
b11 Y
#685000000
0!
0+
0>
0E
0L
0S
#690000000
1!
1+
08
19
b11 <
1>
0A
1B
b10 D
1E
b10 K
1L
b11 M
b0 R
1S
b100 Y
#695000000
0!
0+
0>
b0 D
0E
0L
0S
#700000000
1!
1&
0'
1(
0)
1+
10
01
12
03
1>
b1 D
1E
b11 K
1L
1P
0Q
b1 R
1S
0W
1X
b101 Y
#705000000
0!
0+
0>
0E
0L
0S
#710000000
1!
1+
09
1:
b11 =
1>
0B
1C
b10 D
1E
b100 K
1L
b10 R
1S
b11 T
b0 Y
#715000000
0!
0+
0>
b0 D
0E
0L
0S
#720000000
1!
0%
1'
0(
1*
1+
0/
11
02
14
1>
b1 D
1E
0I
1J
b101 K
1L
b11 R
1S
1W
0X
b1 Y
#725000000
0!
0+
0>
0E
0L
0S
#730000000
1!
0&
1)
1+
00
13
18
0:
b11 ;
1>
1A
0C
b10 D
1E
b11 F
b0 K
1L
0P
1Q
b100 R
1S
b10 Y
#735000000
0!
0+
0>
b0 D
0E
0L
0S
#740000000
1!
b10 $
1%
0*
1+
b10 .
1/
04
1>
b1 D
1E
1I
0J
b1 K
1L
b101 R
1S
b11 Y
#745000000
0!
0+
0>
0E
0L
0S
#750000000
1!
0'
1(
1+
01
12
08
19
b10 <
1>
0A
1B
b10 D
1E
b10 K
1L
b10 M
b0 R
1S
0W
1X
b100 Y
#755000000
0!
0+
0>
b0 D
0E
0L
0S
#760000000
1!
1&
0)
1+
10
03
1>
b1 D
1E
b11 K
1L
1P
0Q
b1 R
1S
b101 Y
#765000000
0!
0+
0>
0E
0L
0S
#770000000
1!
0%
1*
1+
0/
14
09
1:
b10 =
1>
0B
1C
b10 D
1E
0I
1J
b100 K
1L
b10 R
1S
b10 T
b0 Y
#775000000
0!
0+
0>
b0 D
0E
0L
0S
#780000000
1!
0&
1'
0(
1)
1+
00
11
02
13
1>
b1 D
1E
b101 K
1L
0P
1Q
b11 R
1S
1W
0X
b1 Y
#785000000
0!
0+
0>
0E
0L
0S
#790000000
1!
1+
18
0:
b10 ;
1>
1A
0C
b10 D
1E
b10 F
b0 K
1L
b100 R
1S
b10 Y
#795000000
0!
0+
0>
b0 D
0E
0L
0S
#800000000
1!
b1 $
1%
0'
1(
0*
1+
b1 .
1/
01
12
04
1>
b1 D
1E
1I
0J
b1 K
1L
b101 R
1S
0W
1X
b11 Y
#805000000
0!
0+
0>
0E
0L
0S
#810000000
1!
1+
08
19
b1 <
1>
0A
1B
b10 D
1E
b10 K
1L
b1 M
b0 R
1S
b100 Y
#815000000
0!
0+
0>
b0 D
0E
0L
0S
#820000000
1!
0%
1&
0)
1*
1+
0/
10
03
14
1>
b1 D
1E
0I
1J
b11 K
1L
1P
0Q
b1 R
1S
b101 Y
#825000000
0!
0+
0>
0E
0L
0S
#830000000
1!
0&
1)
1+
00
13
09
1:
b1 =
1>
0B
1C
b10 D
1E
b100 K
1L
0P
1Q
b10 R
1S
b1 T
b0 Y
#835000000
0!
0+
0>
b0 D
0E
0L
0S
#840000000
1!
1'
0(
1+
11
02
1>
b1 D
1E
b101 K
1L
b11 R
1S
1W
0X
b1 Y
#845000000
0!
0+
0>
0E
0L
0S
#850000000
1!
0'
1(
1+
01
12
18
0:
b1 ;
1>
1A
0C
b10 D
1E
b1 F
b0 K
1L
b100 R
1S
0W
1X
b10 Y
#855000000
0!
0+
0>
b0 D
0E
0L
0S
#860000000
1!
b0 $
1%
0*
1+
b0 .
1/
04
1>
b1 D
1E
1I
0J
b1 K
1L
b101 R
1S
b11 Y
#865000000
0!
0+
0>
0E
0L
0S
#870000000
1!
0%
1*
1+
0/
14
08
19
b0 <
1>
0A
1B
b10 D
1E
0I
1J
b10 K
1L
b0 M
b0 R
1S
b100 Y
#875000000
0!
0+
0>
b0 D
0E
0L
0S
#880000000
1!
1+
1>
b1 D
1E
b11 K
1L
b1 R
1S
b101 Y
